mixmod/__init__.py
mixmod/estimators.py
mixmod/mixture.py
mixmod-0.2.0.dist-info/LICENSE.txt
mixmod-0.2.0.dist-info/METADATA
mixmod-0.2.0.dist-info/WHEEL
mixmod-0.2.0.dist-info/top_level.txt
mixmod-0.2.0.dist-info/RECORD
