Metadata-Version: 2.1
Name: mixmod
Version: 0.2.0
Summary: An implementation of mixture models with robust fitting methods for a fixed set of components
Home-page: https://github.com/marcsingleton/mixmod
Author: Marc Singleton
Author-email: marcsingleton@berkeley.edu
Classifier: Programming Language :: Python :: 3
Classifier: License :: OSI Approved :: MIT License
Classifier: Operating System :: OS Independent
Requires-Python: >=3.8
License-File: LICENSE.txt
Requires-Dist: numpy (>=1.17)
Requires-Dist: scipy (>=1.8)
